README.md
dualsense.py
setup.cfg
setup.py
dualsense.egg-info/PKG-INFO
dualsense.egg-info/SOURCES.txt
dualsense.egg-info/dependency_links.txt
dualsense.egg-info/requires.txt
dualsense.egg-info/top_level.txt