Metadata-Version: 2.1
Name: dualsense
Version: 0.0.3
Author: Matthew Wildoer
Author-email: mawildoer@gmail.com
License: MIT
